{
    "title": "Coverage Report - take istanbul coverage",
    "htmlPath": "docs/coverage/coverage-0caf5f9c21afe7033814/index.html",
    "type": "istanbul",
    "summary": {
        "lines": {
            "total": 29,
            "covered": 20,
            "skipped": 0,
            "pct": 68.96,
            "status": "medium"
        },
        "statements": {
            "total": 29,
            "covered": 20,
            "skipped": 0,
            "pct": 68.96,
            "status": "medium"
        },
        "functions": {
            "total": 8,
            "covered": 6,
            "skipped": 0,
            "pct": 75,
            "status": "medium"
        },
        "branches": {
            "total": 10,
            "covered": 4,
            "skipped": 0,
            "pct": 40,
            "status": "low"
        },
        "branchesTrue": {
            "total": 0,
            "covered": 0,
            "skipped": 0,
            "pct": "Unknown",
            "status": "unknown"
        }
    },
    "files": [
        {
            "lines": {
                "total": 29,
                "covered": 20,
                "skipped": 0,
                "pct": 68.96,
                "status": "medium"
            },
            "functions": {
                "total": 8,
                "covered": 6,
                "skipped": 0,
                "pct": 75,
                "status": "medium"
            },
            "statements": {
                "total": 29,
                "covered": 20,
                "skipped": 0,
                "pct": 68.96,
                "status": "medium"
            },
            "branches": {
                "total": 10,
                "covered": 4,
                "skipped": 0,
                "pct": 40,
                "status": "low"
            },
            "name": "index.js"
        }
    ]
}
